docsray/__init__.py
docsray/app.py
docsray/auto_restart.py
docsray/auto_setup.py
docsray/chatbot.py
docsray/cli.py
docsray/config.py
docsray/download_models.py
docsray/mcp_server.py
docsray/multimedia_processor.py
docsray/post_install.py
docsray/web_demo.py
docsray/data/mcp_data/config.json
docsray/data/mcp_data/cache/[STOIC] 2025년 서울형 보증연계 RnD 지원사업PPT.pdf_overall_brief.txt
docsray/data/mcp_data/cache/[STOIC] 2025년 서울형 보증연계 RnD 지원사업PPT.pdf_section_0_brief.txt
docsray/inference/__init__.py
docsray/inference/embedding_model.py
docsray/inference/gemma3_handler.py
docsray/inference/llm_model.py
docsray/scripts/__init__.py
docsray/scripts/build_index.py
docsray/scripts/chunker.py
docsray/scripts/file_converter.py
docsray/scripts/pdf_extractor.py
docsray/scripts/section_rep_builder.py
docsray/search/__init__.py
docsray/search/fine_search.py
docsray/search/section_coarse_search.py
docsray/search/vector_search.py
docsray/utils/__init__.py
docsray/utils/pandoc_utils.py
docsray/utils/text_cleaning.py
docsray-1.9.3.dist-info/licenses/LICENSE
docsray-1.9.3.dist-info/METADATA
docsray-1.9.3.dist-info/WHEEL
docsray-1.9.3.dist-info/entry_points.txt
docsray-1.9.3.dist-info/top_level.txt
docsray-1.9.3.dist-info/RECORD
