Metadata-Version: 2.4
Name: docsray
Version: 1.9.3
Summary: Document Question-Answering System with MCP Integration
Author-email: Taehoon Kim <taehoonkim@sogang.ac.kr>
License: MIT
Classifier: Development Status :: 4 - Beta
Classifier: Intended Audience :: Developers
Classifier: License :: OSI Approved :: MIT License
Classifier: Programming Language :: Python :: 3
Classifier: Programming Language :: Python :: 3.8
Classifier: Programming Language :: Python :: 3.9
Classifier: Programming Language :: Python :: 3.10
Classifier: Programming Language :: Python :: 3.11
Classifier: Topic :: Scientific/Engineering :: Artificial Intelligence
Requires-Python: >=3.8
License-File: LICENSE
Requires-Dist: PyMuPDF>=1.23.0
Requires-Dist: pdfplumber>=0.10.0
Requires-Dist: tiktoken>=0.5.0
Requires-Dist: torch>=2.0.0
Requires-Dist: protobuf>=4.0.0
Requires-Dist: fastapi>=0.100.0
Requires-Dist: uvicorn>=0.20.0
Requires-Dist: mcp>=1.0.0
Requires-Dist: numpy>=1.24.0
Requires-Dist: pandas>=2.0.0
Requires-Dist: pillow>=10.0.0
Requires-Dist: scikit-learn>=1.3.0
Requires-Dist: opencv-python>=4.8.0
Requires-Dist: psutil>=5.9.0
Requires-Dist: gradio>=4.0.0
Requires-Dist: pypandoc>=1.11
Requires-Dist: python-pptx>=0.6.21
Requires-Dist: reportlab>=4.0.0
Requires-Dist: Pandoc>=2.3
Requires-Dist: llama_index>=0.9.0
Requires-Dist: pdfkit>=1.0.0
Requires-Dist: openpyxl>=3.1.0
Requires-Dist: olefile>=0.46
Requires-Dist: markdown>=3.4.0
Requires-Dist: beautifulsoup4>=4.12.0
Requires-Dist: faster-whisper>=1.0.0
Provides-Extra: doc
Requires-Dist: python-docx>=0.8.11; extra == "doc"
Requires-Dist: docx2txt>=0.8; extra == "doc"
Dynamic: license-file
